ducktest-0.1.11.dist-info/WHEEL
ducktest-0.1.11.dist-info/DESCRIPTION.rst
ducktest-0.1.11.dist-info/METADATA
ducktest-0.1.11.dist-info/top_level.txt
ducktest-0.1.11.dist-info/metadata.json
ducktest-0.1.11.dist-info/RECORD
ducktest/typing.py
ducktest/__init__.py
ducktest/version.py
ducktest/subtypes.py
ducktest/util.py
ducktest/configuration.py
ducktest/sphinx_docstring.py
ducktest/base.py
