Metadata-Version: 2.0
Name: ducktest
Version: 0.1.11
Summary: Generate type hints from unit tests
Home-page: https://github.com/markuswissinger/ducktestpy
Author: Markus Wissinger
Author-email: markus.wissinger@gmail.com
License: Apache License 2.0
Keywords: development tool type hinting unittest living documentation
Platform: UNKNOWN
Classifier: Development Status :: 3 - Alpha
Classifier: Intended Audience :: Developers
Classifier: Topic :: Software Development
Classifier: License :: OSI Approved :: Apache Software License
Classifier: Programming Language :: Python :: 2.7
Classifier: Programming Language :: Python :: 3.4
Requires-Dist: future
Requires-Dist: mock
